{
  "source_path": "D:/mem/memspine/docs/adr/ADR-023-pluggable-secrets-aws.md",
  "type": "ADR",
  "confidence": "high",
  "manifest_override": false,
  "title": "ADR-023 — Pluggable secrets resolver + AWS Secrets Manager",
  "summary": "Adds pluggable secrets resolvers (AWS Secrets Manager, chained) selected via env var during pre-config bootstrap phase 1.",
  "scope": ["SecretsService", "AwsSecrets", "ChainedSecrets", "EnvSecrets", "AWS Secrets Manager", "bootstrap secrets", "boto3", "[aws] extra"],
  "cross_refs": [],
  "locked": true,
  "precedence": null,
  "notes": ""
}
